epyestim/__init__.py
epyestim/bootstrap.py
epyestim/covid19.py
epyestim/deconvolution.py
epyestim/distributions.py
epyestim/estimate_r.py
epyestim/main.py
epyestim/smoothen.py
epyestim-0.1.dist-info/LICENSE
epyestim-0.1.dist-info/METADATA
epyestim-0.1.dist-info/WHEEL
epyestim-0.1.dist-info/top_level.txt
epyestim-0.1.dist-info/RECORD
