Metadata-Version: 2.1
Name: epyestim
Version: 0.1
Summary: UNKNOWN
Home-page: https://github.com/lo-hfk/epyestim
License: MIT License
Platform: UNKNOWN
Requires-Dist: pandas
Requires-Dist: numpy
Requires-Dist: scipy
Requires-Dist: statsmodels
Provides-Extra: tests
Requires-Dist: pytest ; extra == 'tests'
